[{"type":"store",
 "name":"Tienda de preba tarea",
 "address":"14 calle 34-23 zona 18",
 "phone":"5555-7978",
 "hoursOfOperaion":"Lunes a viernes de 8AM a 8PM",
 "url":"http://www.latiendadelibros.com",
 "email":"info@latiendadelibros.com",
 "comments":[
        {"comment":"mi lugar favorito"},
        {"comment":"excelentes ofertas"}],
 "favorites":20,
 "location":[{"lat":14.61,"lon":-90.50}]},
{"type":"store",
 "name":"Tienda de tarea dia martes",
 "address":"6 avenida 8-10 zona 10",
 "phone":"5067-4512",
 "hoursOfOperaion":"Lunes a Viernes de 10AM a 9PM\nSabado y Domingo de 10AM a 10PM",
 "url":"",
 "email":"tiendaderopa@gmail.com",
 "comments":[
        {"comment":"siempre tienen productos nuevos"},
        {"comment":"muy buen servicio al cliente"}],
 "favorites":20,
 "location":[{"lat":14.62,"lon":-90.56}]},
{"type":"photo",
 "url":"https://www.google.com/images/srpr/logo11w.png",
 "description":"Logo de Google",
 "favorites":4
}]